LICENSE
MANIFEST.in
README.md
setup.py
unittesthtmlreport.egg-info/PKG-INFO
unittesthtmlreport.egg-info/SOURCES.txt
unittesthtmlreport.egg-info/dependency_links.txt
unittesthtmlreport.egg-info/requires.txt
unittesthtmlreport.egg-info/top_level.txt
unittestreport/__init__.py
unittestreport/core/__init__.py
unittestreport/core/dataDriver.py
unittestreport/core/parameterized.py
unittestreport/core/reRun.py
unittestreport/core/resultPush.py
unittestreport/core/sendEmail.py
unittestreport/core/testResult.py
unittestreport/core/testRunner.py
unittestreport/templates/__init__.py
unittestreport/templates/dingtalk.md
unittestreport/templates/templates.html
unittestreport/templates/templates03.html
unittestreport/templates/templates2.html
unittestreport/templates/templates3.html