Metadata-Version: 2.1
Name: unittesthtmlreport
Version: 1.5.1
Home-page: https://github.com/musen123/UnitTestReport
Author: MuSen
Author-email: musen_nmb@qq.com
Classifier: Programming Language :: Python :: 3
Requires-Python: >=3.6
License-File: LICENSE
